sppm_cli.py
sppm/__init__.py
sppm/child.py
sppm/cmd_action.py
sppm/master.py
sppm/process_status.py
sppm/process_status_lock.py
sppm/settings.py
sppm/signal_handler.py
sppm/sppm_config.py
sppm/utils.py
sppm_help/__init__.py
sppm_help/version.txt
sppm-2.1.4.dist-info/LICENSE
sppm-2.1.4.dist-info/METADATA
sppm-2.1.4.dist-info/WHEEL
sppm-2.1.4.dist-info/entry_points.txt
sppm-2.1.4.dist-info/top_level.txt
sppm-2.1.4.dist-info/RECORD
