Metadata-Version: 2.1
Name: sppm
Version: 2.1.4
Summary: 一个简化进程管理的 Python 库，丰富的命令行控制参数满足各种运行需求
Author-email: Chengdu Geek Camp <lq@cdgeekcamp.com>
License: MIT
Project-URL: Documentation, https://github.com/geekcampchina/SamplePythonProcessManager
Project-URL: Source, https://github.com/geekcampchina/SamplePythonProcessManager
Project-URL: Home-page, https://github.com/geekcampchina/SamplePythonProcessManager
Platform: Linux
Classifier: Operating System :: POSIX :: Linux
Classifier: Intended Audience :: Developers
Classifier: License :: OSI Approved :: MIT License
Classifier: Operating System :: OS Independent
Classifier: Programming Language :: Python
Classifier: Programming Language :: Python :: 3
Classifier: Topic :: Software Development :: Libraries :: Python Modules
Requires-Python: >=3.8.5
License-File: LICENSE
Requires-Dist: python-daemon
Requires-Dist: happy-python
Requires-Dist: psutil
Requires-Dist: setproctitle
